elabftw_usersync/__init__.py
elabftw_usersync/elabftw.py
elabftw_usersync/helper.py
elabftw_usersync/idm_ldap.py
elabftw_usersync/logger_config.py
elabftw_usersync/main.py
elabftw_usersync/processing.py
tests/__init__.py
tests/test_elabftw.py
tests/test_helper.py
tests/test_idm_ldap.py
elabftw_usersync-1.0.1.dist-info/LICENSE
elabftw_usersync-1.0.1.dist-info/METADATA
elabftw_usersync-1.0.1.dist-info/WHEEL
elabftw_usersync-1.0.1.dist-info/entry_points.txt
elabftw_usersync-1.0.1.dist-info/top_level.txt
elabftw_usersync-1.0.1.dist-info/RECORD
