Metadata-Version: 2.1
Name: elabftw_usersync
Version: 1.0.1
Summary: Sync Script that reads user data from an LDAP Server and creates users in an elabFTW instance
Home-page: https://github.com/ulbmuenster/eln-ldap-sync
Author: ULB Münster
Author-email: fdm@uni-muenster.de
License: MIT
License-File: LICENSE
Requires-Dist: python-ldap
Requires-Dist: requests
Requires-Dist: progress
Requires-Dist: python-dotenv
Requires-Dist: loguru
Requires-Dist: click
